Workbook

Sheet 全台股
A1: ID | B1: Name | C1: Year | D1: Assets | E1: STD | F1: CPLTD | G1: LTD | H1: EBITDA | I1: Sales | J1: Sales_YOY | K1: FCF | L1: CapEx | M1: Int | N1: TIE | O1: CR | P1: FX | Q1: Industry
A2: 1101 | B2: 台泥 | C2: 2024 | D2: 593413647 | E2: 24292290 | F2: 9307637 | G2: 61287926 | H2: 44556263 | I2: 154606511 | J2: 0.4143 | K2: -7979225 | L2: -33603520 | M2: 0.2649 | N2: 5.35 | O2: 200.73 | P2: 2488775 | Q2: =_xlfn.XLOOKUP(A2,工作表1!$A:$A,工作表1!$Q:$Q) -> 水泥製造
A3: 1101 | B3: 台泥 | C3: 2023 | D3: 469438522 | E3: 20251073 | F3: 13859614 | G3: 36791733 | H3: 27184237 | I3: 109314335 | J3: -0.0405 | K3: 14445652 | L3: -24726266 | M3: 0.2759 | N3: 5.05 | O3: 210.95 | P3: -838432 | Q3: =_xlfn.XLOOKUP(A3,工作表1!$A:$A,工作表1!$Q:$Q) -> 水泥製造
A4: 1101 | B4: 台泥 | C4: 2022 | D4: 460808961 | E4: 22416812 | F4: 21511839 | G4: 42864736 | H4: 18043816 | I4: 113929706 | J4: 0.0644 | K4: -30522717 | L4: -23458453 | M4: 0.4447 | N4: 3.32 | O4: 233.51 | P4: 2088653 | Q4: =_xlfn.XLOOKUP(A4,工作表1!$A:$A,工作表1!$Q:$Q) -> 水泥製造
A5: 1102 | B5: 亞泥 | C5: 2024 | D5: 331827224 | E5: 26488506 | F5: 18871785 | G5: 8926787 | H5: 22257323 | I5: 81848827 | J5: -0.0087 | K5: 15731708 | L5: -4003258 | M5: 0.1192 | N5: 10.6 | O5: 146.4 | P5: 1397272 | Q5: =_xlfn.XLOOKUP(A5,工作表1!$A:$A,工作表1!$Q:$Q) -> 水泥製造
A6: 1102 | B6: 亞泥 | C6: 2023 | D6: 336726851 | E6: 29016580 | F6: 10219160 | G6: 9567454 | H6: 20464516 | I6: 82564009 | J6: -0.0939 | K6: 12791788 | L6: -4081969 | M6: 0.1418 | N6: 8.86 | O6: 147.6 | P6: -394244 | Q6: =_xlfn.XLOOKUP(A6,工作表1!$A:$A,工作表1!$Q:$Q) -> 水泥製造
A7: 1102 | B7: 亞泥 | C7: 2022 | D7: 324243127 | E7: 28692869 | F7: 1593990 | G7: 10415840 | H7: 21261387 | I7: 91122104 | J7: -0.031 | K7: 9086417 | L7: -2666315 | M7: 0.095 | N7: 12.73 | O7: 157.05 | P7: 1089038 | Q7: =_xlfn.XLOOKUP(A7,工作表1!$A:$A,工作表1!$Q:$Q) -> 水泥製造
A8: 1103 | B8: 嘉泥 | C8: 2024 | D8: 35078080 | E8: 885000 | F8: 1055745 | G8: 6879673 | H8: 1049811 | I8: 2985357 | J8: 0.0253 | K8: 1058475 | L8: -51631 | M8: 0.423 | N8: 2.79 | O8: 336.63 | P8: 46319 | Q8: =_xlfn.XLOOKUP(A8,工作表1!$A:$A,工作表1!$Q:$Q) -> 水泥製造
A9: 1103 | B9: 嘉泥 | C9: 2023 | D9: 36464334 | E9: 1356040 | F9: 571452 | G9: 7386018 | H9: 745243 | I9: 2911583 | J9: 0.2919 | K9: 219756 | L9: -51589 | M9: 0.7865 | N9: 1.41 | O9: 319.5 | P9: -52445 | Q9: =_xlfn.XLOOKUP(A9,工作表1!$A:$A,工作表1!$Q:$Q) -> 水泥製造
A10: 1103 | B10: 嘉泥 | C10: 2022 | D10: 36454234 | E10: 1673664 | F10: 933090 | G10: 7439628 | H10: 545575 | I10: 2253659 | J10: 0.015 | K10: 1671514 | L10: -55508 | M10: -4.4199 | N10: 0.28 | O10: 302.94 | P10: 208074 | Q10: =_xlfn.XLOOKUP(A10,工作表1!$A:$A,工作表1!$Q:$Q) -> 水泥製造
A11: 1104 | B11: 環泥 | C11: 2024 | D11: 29627506 | E11: 2100000 | F11: 0 | G11: 0 | H11: 2070596 | I11: 7953734 | J11: 0.0194 | K11: 948645 | L11: -179647 | M11: 0.0274 | N11: 43.09 | O11: 188.97 | P11: 0 | Q11: =_xlfn.XLOOKUP(A11,工作表1!$A:$A,工作表1!$Q:$Q) -> 水泥製造
A12: 1104 | B12: 環泥 | C12: 2023 | D12: 28189560 | E12: 1700000 | F12: 500000 | G12: 0 | H12: 2824162 | I12: 7802362 | J12: 0.1058 | K12: 477272 | L12: -195570 | M12: 0.0233 | N12: 47.39 | O12: 167.61 | P12: 0 | Q12: =_xlfn.XLOOKUP(A12,工作表1!$A:$A,工作表1!$Q:$Q) -> 水泥製造
A13: 1104 | B13: 環泥 | C13: 2022 | D13: 27811895 | E13: 2290000 | F13: 0 | G13: 0 | H13: 2603027 | I13: 7055789 | J13: 0.1607 | K13: 1903651 | L13: -320210 | M13: 0.0188 | N13: 58.19 | O13: 118.88 | P13: 0 | Q13: =_xlfn.XLOOKUP(A13,工作表1!$A:$A,工作表1!$Q:$Q) -> 水泥製造
... A373: 1526 | B373: 日馳 | C373: 2022 | D373: 2904399 | E373: 294560 | F373: 5326 | G373: 332505 | H373: 581227 | I373: 2197117 | J373: 0.164 | K373: 370695 | L373: -80994 | M373: 0.0249 | N373: 51.27 | O373: 183.91 | P373: 29889 | Q373: =_xlfn.XLOOKUP(A373,工作表1!$A:$A,工作表1!$Q:$Q) -> 自行車組件
A374: 1527 | B374: 鑽全 | C374: 2024 | D374: 5558752 | E374: 0 | F374: 0 | G374: 0 | H374: 682523 | I374: 3130242 | J374: 0.1243 | K374: 842032 | L374: -140094 | M374: 0 | O374: 591.17 | P374: 0 | Q374: =_xlfn.XLOOKUP(A374,工作表1!$A:$A,工作表1!$Q:$Q) -> 工具機
A375: 1527 | B375: 鑽全 | C375: 2023 | D375: 5288545 | E375: 0 | F375: 0 | G375: 0 | H375: 584941 | I375: 2784110 | J375: -0.2895 | K375: 512467 | L375: -105534 | M375: 0 | O375: 764.46 | P375: 0 | Q375: =_xlfn.XLOOKUP(A375,工作表1!$A:$A,工作表1!$Q:$Q) -> 工具機
A376: 1527 | B376: 鑽全 | C376: 2022 | D376: 5406694 | E376: 0 | F376: 0 | G376: 0 | H376: 1061051 | I376: 3918677 | J376: -0.1262 | K376: 377834 | L376: -43045 | M376: 0 | O376: 656.75 | P376: 0 | Q376: =_xlfn.XLOOKUP(A376,工作表1!$A:$A,工作表1!$Q:$Q) -> 工具機
A377: 1528 | B377: 恩德 | C377: 2024 | D377: 5305871 | E377: 1542608 | F377: 268122 | G377: 355633 | H377: 42020 | I377: 3672594 | J377: -0.0542 | K377: 207148 | L377: -113543 | M377: -0.5333 | N377: -1.57 | O377: 141.47 | P377: 9149 | Q377: =_xlfn.XLOOKUP(A377,工作表1!$A:$A,工作表1!$Q:$Q) -> 工具機
A378: 1528 | B378: 恩德 | C378: 2023 | D378: 5556368 | E378: 1473390 | F378: 221893 | G378: 457494 | H378: 188428 | I378: 3883131 | J378: 0.0248 | K378: -3345 | L378: -56035 | M378: 5.0485 | N378: 0.99 | O378: 156.08 | P378: 5002 | Q378: =_xlfn.XLOOKUP(A378,工作表1!$A:$A,工作表1!$Q:$Q) -> 工具機
A379: 1528 | B379: 恩德 | C379: 2022 | D379: 5559022 | E379: 1416518 | F379: 147649 | G379: 391208 | H379: 367330 | I379: 3789118 | J379: 0.0562 | K379: 178780 | L379: -117011 | M379: 0.2028 | N379: 6.6 | O379: 152.57 | P379: 48203 | Q379: =_xlfn.XLOOKUP(A379,工作表1!$A:$A,工作表1!$Q:$Q) -> 工具機
A380: 1529 | B380: 樂事綠能 | C380: 2024 | D380: 3384566 | E380: 275000 | F380: 62389 | G380: 816396 | H380: 143995 | I380: 696439 | J380: -0.0743 | K380: 86963 | L380: -200327 | M380: 7.1849 | N380: 0.9 | O380: 159.65 | P380: 0 | Q380: =_xlfn.XLOOKUP(A380,工作表1!$A:$A,工作表1!$Q:$Q) -> 電機
A381: 1529 | B381: 樂事綠能 | C381: 2023 | D381: 3137634 | E381: 171271 | F381: 63368 | G381: 777783 | H381: 269769 | I381: 752370 | J381: 1.6725 | K381: 12120 | L381: -244510 | M381: 0.1389 | N381: 7.81 | O381: 233.73 | P381: 0 | Q381: =_xlfn.XLOOKUP(A381,工作表1!$A:$A,工作表1!$Q:$Q) -> 電機
A382: 1529 | B382: 樂事綠能 | C382: 2022 | D382: 2999128 | E382: 240640 | F382: 47081 | G382: 699303 | H382: 121462 | I382: 281520 | J382: -0.1323 | K382: -388864 | L382: -476445 | M382: 0.2003 | N382: 6.08 | O382: 223.15 | P382: 221 | Q382: =_xlfn.XLOOKUP(A382,工作表1!$A:$A,工作表1!$Q:$Q) -> 電機
A383: 1530 | B383: 亞崴 | C383: 2024 | D383: 6393258 | E383: 1613983 | F383: 0 | G383: 0 | H383: 598714 | I383: 1917762 | J383: -0.188 | K383: 154770 | L383: -183694 | M383: 0.0665 | N383: 15.59 | O383: 166.88 | P383: 14778 | Q383: =_xlfn.XLOOKUP(A383,工作表1!$A:$A,工作表1!$Q:$Q) -> 工具機
A384: 1530 | B384: 亞崴 | C384: 2023 | D384: 5961891 | E384: 1576852 | F384: 0 | G384: 0 | H384: 382397 | I384: 2361917 | J384: -0.2382 | K384: 201950 | L384: -54542 | M384: 0.1513 | N384: 8.18 | O384: 155.93 | P384: -9215 | Q384: =_xlfn.XLOOKUP(A384,工作表1!$A:$A,工作表1!$Q:$Q) -> 工具機
A385: 1530 | B385: 亞崴 | C385: 2022 | D385: 6791798 | E385: 1954949 | F385: 0 | G385: 0 | H385: 603835 | I385: 3100517 | J385: -0.1461 | K385: 163337 | L385: -22340 | M385: 0.0703 | N385: 18.68 | O385: 140.01 | P385: 2219 | Q385: =_xlfn.XLOOKUP(A385,工作表1!$A:$A,工作表1!$Q:$Q) -> 工具機
A386: 1531 | B386: 高林股 | C386: 2024 | D386: 4371229 | E386: 100000 | F386: 0 | G386: 0 | H386: 188585 | I386: 1637783 | J386: 0.1529 | K386: -42814 | L386: -47070 | M386: 0.0265 | N386: 47.8 | O386: 805.97 | P386: 18550 | Q386: =_xlfn.XLOOKUP(A386,工作表1!$A:$A,工作表1!$Q:$Q) -> 紡織工具機
A387: 1531 | B387: 高林股 | C387: 2023 | D387: 4167691 | E387: 100000 | F387: 0 | G387: 0 | H387: 36591 | I387: 1420562 | J387: -0.4251 | K387: -87455 | L387: -211309 | M387: -0.088 | N387: -9.31 | O387: 796.73 | P387: -21161 | Q387: =_xlfn.XLOOKUP(A387,工作表1!$A:$A,工作表1!$Q:$Q) -> 紡織工具機
A388: 1531 | B388: 高林股 | C388: 2022 | D388: 4610206 | E388: 253549 | F388: 0 | G388: 0 | H388: 342054 | I388: 2471056 | J388: -0.1615 | K388: 160266 | L388: -22306 | M388: 0.0419 | N388: 33.06 | O388: 503.89 | P388: 16759 | Q388: =_xlfn.XLOOKUP(A388,工作表1!$A:$A,工作表1!$Q:$Q) -> 紡織工具機
... A409: 1539 | B409: 巨庭 | C409: 2022 | D409: 2648548 | E409: 256500 | F409: 74192 | G409: 321615 | H409: 542594 | I409: 2500079 | J409: -0.2045 | K409: 112896 | L409: -18412 | M409: 0.033 | N409: 36.73 | O409: 231.18 | P409: -4457 | Q409: =_xlfn.XLOOKUP(A409,工作表1!$A:$A,工作表1!$Q:$Q) -> 工具機
A410: 1540 | B410: 喬福 | C410: 2024 | D410: 1828680 | E410: 0 | F410: 0 | G410: 0 | H410: 234524 | I410: 498100 | J410: -0.1348 | K410: 80913 | L410: -4442 | M410: 0 | O410: 515.34 | P410: -73 | Q410: =_xlfn.XLOOKUP(A410,工作表1!$A:$A,工作表1!$Q:$Q) -> 工具機
A411: 1540 | B411: 喬福 | C411: 2023 | D411: 1718663 | E411: 0 | F411: 0 | G411: 0 | H411: 152768 | I411: 575699 | J411: 0.2164 | K411: 59792 | L411: -1653 | M411: 0 | O411: 494.49 | P411: -315 | Q411: =_xlfn.XLOOKUP(A411,工作表1!$A:$A,工作表1!$Q:$Q) -> 工具機
A412: 1540 | B412: 喬福 | C412: 2022 | D412: 1559314 | E412: 0 | F412: 0 | G412: 0 | H412: 143149 | I412: 473291 | J412: 0.3118 | K412: 23912 | L412: -1281 | M412: 0.0002 | N412: 7511.11 | O412: 711.35 | P412: 34624 | Q412: =_xlfn.XLOOKUP(A412,工作表1!$A:$A,工作表1!$Q:$Q) -> 工具機
A413: 1541 | B413: 錩泰 | C413: 2024 | D413: 3157599 | E413: 16000 | F413: 0 | G413: 0 | H413: 239701 | I413: 2988448 | J413: -0.1153 | K413: 221713 | L413: -12468 | M413: 0.1936 | N413: 6.13 | O413: 242.43 | P413: 30229 | Q413: =_xlfn.XLOOKUP(A413,工作表1!$A:$A,工作表1!$Q:$Q) -> 工具機
A414: 1541 | B414: 錩泰 | C414: 2023 | D414: 3978257 | E414: 569700 | F414: 0 | G414: 0 | H414: 282559 | I414: 3378030 | J414: -0.1674 | K414: 286884 | L414: -27926 | M414: 0.1449 | N414: 8.74 | O414: 175.02 | P414: -26 | Q414: =_xlfn.XLOOKUP(A414,工作表1!$A:$A,工作表1!$Q:$Q) -> 工具機
A415: 1541 | B415: 錩泰 | C415: 2022 | D415: 3611116 | E415: 544000 | F415: 0 | G415: 0 | H415: 495924 | I415: 4057447 | J415: -0.3459 | K415: 224559 | L415: -42134 | M415: 0.0775 | N415: 16.84 | O415: 193.21 | P415: 11700 | Q415: =_xlfn.XLOOKUP(A415,工作表1!$A:$A,工作表1!$Q:$Q) -> 工具機
A416: 1558 | B416: 伸興 | C416: 2024 | D416: 13140704 | E416: 906000 | F416: 107525 | G416: 616177 | H416: 1885894 | I416: 8337227 | J416: 0.1031 | K416: 1357424 | L416: -451003 | M416: 0.0234 | N416: 55.8 | O416: 225.4 | P416: 61794 | Q416: =_xlfn.XLOOKUP(A416,工作表1!$A:$A,工作表1!$Q:$Q) -> 紡織工具機
A417: 1558 | B417: 伸興 | C417: 2023 | D417: 11995154 | E417: 393000 | F417: 132525 | G417: 723702 | H417: 1424530 | I417: 7558277 | J417: 0.05 | K417: 1122626 | L417: -118606 | M417: 0.033 | N417: 33.98 | O417: 274.56 | P417: -44279 | Q417: =_xlfn.XLOOKUP(A417,工作表1!$A:$A,工作表1!$Q:$Q) -> 紡織工具機
A418: 1558 | B418: 伸興 | C418: 2022 | D418: 13244676 | E418: 1438492 | F418: 152454 | G418: 613905 | H418: 1290415 | I418: 7198245 | J418: -0.0676 | K418: 59030 | L418: -250643 | M418: 0.0437 | N418: 29.61 | O418: 212.28 | P418: 65111 | Q418: =_xlfn.XLOOKUP(A418,工作表1!$A:$A,工作表1!$Q:$Q) -> 紡織工具機
A419: 1560 | B419: 中砂 | C419: 2024 | D419: 11050863 | E419: 60500 | F419: 14383 | G419: 1078219 | H419: 1910886 | I419: 7019493 | J419: 0.1001 | K419: -678805 | L419: -348508 | M419: 0.0402 | N419: 30.23 | O419: 355.04 | P419: 26268 | Q419: =_xlfn.XLOOKUP(A419,工作表1!$A:$A,工作表1!$Q:$Q) -> 晶圓材料
A420: 1560 | B420: 中砂 | C420: 2023 | D420: 9862953 | E420: 955000 | F420: 0 | G420: 1014000 | H420: 1710132 | I420: 6380904 | J420: -0.0763 | K420: 1223851 | L420: -532349 | M420: 0.0477 | N420: 25.81 | O420: 179.59 | P420: -1114 | Q420: =_xlfn.XLOOKUP(A420,工作表1!$A:$A,工作表1!$Q:$Q) -> 晶圓材料
A421: 1560 | B421: 中砂 | C421: 2022 | D421: 9544895 | E421: 100000 | F421: 500000 | G421: 1300000 | H421: 2214891 | I421: 6907619 | J421: 0.146 | K421: 1596951 | L421: -191746 | M421: 0.0301 | N421: 40.57 | O421: 204.8 | P421: 20813 | Q421: =_xlfn.XLOOKUP(A421,工作表1!$A:$A,工作表1!$Q:$Q) -> 晶圓材料
A422: 1563 | B422: 巧新 | C422: 2024 | D422: 17519544 | E422: 1003535 | F422: 1027626 | G422: 4260544 | H422: 2017197 | I422: 7473579 | J422: -0.0393 | K422: 219882 | L422: -487406 | M422: 0.1782 | N422: 7.01 | O422: 273.06 | P422: -1036 | Q422: =_xlfn.XLOOKUP(A422,工作表1!$A:$A,工作表1!$Q:$Q) -> 汽車組件
A423: 1563 | B423: 巧新 | C423: 2023 | D423: 17376064 | E423: 965144 | F423: 1231388 | G423: 5894400 | H423: 1896761 | I423: 7779316 | J423: 0.2152 | K423: 888458 | L423: -729154 | M423: 0.2337 | N423: 5.36 | O423: 233.16 | P423: 7348 | Q423: =_xlfn.XLOOKUP(A423,工作表1!$A:$A,工作表1!$Q:$Q) -> 汽車組件
... A616: 1781 | B616: 合世 | C616: 2022 | D616: 799759 | E616: 116566 | F616: 12612 | G616: 31529 | H616: 11847 | I616: 797542 | J616: -0.0177 | K616: 33284 | L616: -4740 | M616: -0.2086 | N616: -3.93 | O616: 153.07 | P616: 21733 | Q616: =_xlfn.XLOOKUP(A616,工作表1!$A:$A,工作表1!$Q:$Q) -> 診斷與監測
A617: 1783 | B617: 和康生 | C617: 2024 | D617: 1582489 | E617: 0 | F617: 0 | G617: 0 | H617: 252569 | I617: 680651 | J617: 0.0941 | K617: 49145 | L617: -31771 | M617: 0 | O617: 403.33 | P617: -1450 | Q617: =_xlfn.XLOOKUP(A617,工作表1!$A:$A,工作表1!$Q:$Q) -> 輔助與彌補
A618: 1783 | B618: 和康生 | C618: 2023 | D618: 1492986 | E618: 0 | F618: 0 | G618: 0 | H618: 220758 | I618: 622115 | J618: 0.0293 | K618: 524559 | L618: -22441 | M618: 0 | O618: 471.61 | P618: 573 | Q618: =_xlfn.XLOOKUP(A618,工作表1!$A:$A,工作表1!$Q:$Q) -> 輔助與彌補
A619: 1783 | B619: 和康生 | C619: 2022 | D619: 1447723 | E619: 0 | F619: 0 | G619: 0 | H619: 195430 | I619: 604431 | J619: 0.1806 | K619: -19567 | L619: -14292 | M619: 0.0005 | N619: 2438.94 | O619: 655.61 | P619: -76 | Q619: =_xlfn.XLOOKUP(A619,工作表1!$A:$A,工作表1!$Q:$Q) -> 輔助與彌補
A620: 1784 | B620: 訊聯 | C620: 2024 | D620: 3156241 | E620: 65000 | F620: 0 | G620: 0 | H620: 149085 | I620: 1222030 | J620: 0.084 | K620: -647066 | L620: -101347 | M620: 0.018 | N620: 80.94 | O620: 506.19 | P620: 491 | Q620: =_xlfn.XLOOKUP(A620,工作表1!$A:$A,工作表1!$Q:$Q) -> 細胞醫療
A621: 1784 | B621: 訊聯 | C621: 2023 | D621: 2348639 | E621: 30000 | F621: 0 | G621: 0 | H621: 147099 | I621: 1127304 | J621: 0.1499 | K621: -338695 | L621: -20043 | M621: 0.005 | N621: 262.18 | O621: 390.33 | P621: -268 | Q621: =_xlfn.XLOOKUP(A621,工作表1!$A:$A,工作表1!$Q:$Q) -> 細胞醫療
A622: 1784 | B622: 訊聯 | C622: 2022 | D622: 1838690 | E622: 0 | F622: 0 | G622: 0 | H622: 113968 | I622: 980377 | J622: 0.064 | K622: 2109 | L622: -28874 | M622: 0.0085 | N622: 154.83 | O622: 306.17 | P622: -31 | Q622: =_xlfn.XLOOKUP(A622,工作表1!$A:$A,工作表1!$Q:$Q) -> 細胞醫療
A623: 1785 | B623: 光洋科 | C623: 2024 | D623: 31292876 | E623: 4146089 | F623: 2886031 | G623: 5022938 | H623: 3311330 | I623: 29769958 | J623: 0.3156 | K623: 1938557 | L623: -553077 | M623: 0.1422 | N623: 8.75 | O623: 193.84 | P623: 98855 | Q623: =_xlfn.XLOOKUP(A623,工作表1!$A:$A,工作表1!$Q:$Q) -> 貴金屬回收
A624: 1785 | B624: 光洋科 | C624: 2023 | D624: 26459683 | E624: 2842587 | F624: 1418269 | G624: 5726080 | H624: 2236732 | I624: 22629192 | J624: -0.1226 | K624: 1748337 | L624: -832963 | M624: 0.2698 | N624: 4.51 | O624: 262.36 | P624: -50440 | Q624: =_xlfn.XLOOKUP(A624,工作表1!$A:$A,工作表1!$Q:$Q) -> 貴金屬回收
A625: 1785 | B625: 光洋科 | C625: 2022 | D625: 26569543 | E625: 1445145 | F625: 1019937 | G625: 6770952 | H625: 2423522 | I625: 25790594 | J625: -0.1775 | K625: 1541824 | L625: -1373538 | M625: 0.1584 | N625: 7.44 | O625: 317.84 | P625: 41803 | Q625: =_xlfn.XLOOKUP(A625,工作表1!$A:$A,工作表1!$Q:$Q) -> 貴金屬回收
A626: 1786 | B626: 科妍 | C626: 2024 | D626: 2354476 | E626: 0 | F626: 134785 | G626: 0 | H626: 362499 | I626: 883310 | J626: 0.2389 | K626: 302287 | L626: -34763 | M626: 0.023 | N626: 52.4 | O626: 346.05 | P626: 50 | Q626: =_xlfn.XLOOKUP(A626,工作表1!$A:$A,工作表1!$Q:$Q) -> 輔助與彌補
A627: 1786 | B627: 科妍 | C627: 2023 | D627: 2160170 | E627: 0 | F627: 0 | G627: 0 | H627: 281348 | I627: 712988 | J627: 0.2793 | K627: 120328 | L627: -14734 | M627: 0.0446 | N627: 26.55 | O627: 692.39 | P627: -33 | Q627: =_xlfn.XLOOKUP(A627,工作表1!$A:$A,工作表1!$Q:$Q) -> 輔助與彌補
A628: 1786 | B628: 科妍 | C628: 2022 | D628: 2098236 | E628: 0 | F628: 0 | G628: 0 | H628: 242066 | I628: 557348 | J628: 0.1025 | K628: -64534 | L628: -14964 | M628: 0.044 | N628: 27.87 | O628: 687.86 | P628: 14 | Q628: =_xlfn.XLOOKUP(A628,工作表1!$A:$A,工作表1!$Q:$Q) -> 輔助與彌補
A629: 1788 | B629: 杏昌 | C629: 2024 | D629: 4960390 | E629: 367987 | F629: 0 | G629: 0 | H629: 647829 | I629: 4072811 | J629: 0.0454 | K629: 560444 | L629: -282741 | M629: 0.0373 | N629: 33.95 | O629: 177.17 | P629: 3124 | Q629: =_xlfn.XLOOKUP(A629,工作表1!$A:$A,工作表1!$Q:$Q) -> 手術與治療
A630: 1788 | B630: 杏昌 | C630: 2023 | D630: 4617885 | E630: 91565 | F630: 0 | G630: 12357 | H630: 611502 | I630: 3895778 | J630: -0.1693 | K630: -27529 | L630: -61950 | M630: 0.0348 | N630: 35.91 | O630: 223.49 | P630: -1683 | Q630: =_xlfn.XLOOKUP(A630,工作表1!$A:$A,工作表1!$Q:$Q) -> 手術與治療
... A734: 2025 | B734: 千興 | C734: 2024 | D734: 1549946 | E734: 0 | F734: 0 | G734: 0 | H734: -205073 | I734: 1058326 | J734: 0.4327 | K734: -55191 | L734: -48513 | M734: -0.001 | N734: -991.49 | O734: 1283.12 | P734: 276 | Q734: =_xlfn.XLOOKUP(A734,工作表1!$A:$A,工作表1!$Q:$Q) -> 不鏽鋼
A735: 2025 | B735: 千興 | C735: 2023 | D735: 1804927 | E735: 0 | F735: 0 | G735: 0 | H735: 280874 | I735: 738691 | J735: -0.3999 | K735: -23606 | L735: -18703 | M735: 0 | O735: 1353.46 | P735: -32 | Q735: =_xlfn.XLOOKUP(A735,工作表1!$A:$A,工作表1!$Q:$Q) -> 不鏽鋼
A736: 2025 | B736: 千興 | C736: 2022 | D736: 1516431 | E736: 0 | F736: 0 | G736: 0 | H736: 924038 | I736: 1231007 | J736: -0.5018 | K736: 150699 | L736: -9367 | M736: 0.0094 | N736: 110.96 | O736: 2172.19 | P736: 81 | Q736: =_xlfn.XLOOKUP(A736,工作表1!$A:$A,工作表1!$Q:$Q) -> 不鏽鋼
A737: 2027 | B737: 大成鋼 | C737: 2024 | D737: 137747714 | E737: 13156899 | F737: 1416103 | G737: 23139294 | H737: 10926923 | I737: 90398484 | J737: -0.1072 | K737: 1145678 | L737: -8506317 | M737: 0.1956 | N737: 7 | O737: 322.55 | P737: 266029 | Q737: =_xlfn.XLOOKUP(A737,工作表1!$A:$A,工作表1!$Q:$Q) -> 不鏽鋼
A738: 2027 | B738: 大成鋼 | C738: 2023 | D738: 135115312 | E738: 17955293 | F738: 1274888 | G738: 22870654 | H738: 13787088 | I738: 101256601 | J738: -0.1129 | K738: 13050358 | L738: -7356935 | M738: 0.1619 | N738: 8.58 | O738: 292.68 | P738: 57126 | Q738: =_xlfn.XLOOKUP(A738,工作表1!$A:$A,工作表1!$Q:$Q) -> 不鏽鋼
A739: 2027 | B739: 大成鋼 | C739: 2022 | D739: 146446086 | E739: 13650609 | F739: 9066292 | G739: 28987572 | H739: 22862802 | I739: 114148570 | J739: 0.1782 | K739: -223330 | L739: -8555520 | M739: 0.0791 | N739: 16.78 | O739: 287.75 | P739: 406224 | Q739: =_xlfn.XLOOKUP(A739,工作表1!$A:$A,工作表1!$Q:$Q) -> 不鏽鋼
A740: 2028 | B740: 威致 | C740: 2024 | D740: 9912163 | E740: 1193183 | F740: 191979 | G740: 1802332 | H740: 778456 | I740: 10196132 | J740: -0.0275 | K740: -319389 | L740: -977627 | M740: 0.161 | N740: 7.22 | O740: 154.93 | P740: 0 | Q740: =_xlfn.XLOOKUP(A740,工作表1!$A:$A,工作表1!$Q:$Q) -> 鋼筋
A741: 2028 | B741: 威致 | C741: 2023 | D741: 8645106 | E741: 593149 | F741: 167885 | G741: 1386083 | H741: 806922 | I741: 10484173 | J741: -0.2011 | K741: 199170 | L741: -703361 | M741: 0.0946 | N741: 12.75 | O741: 167.72 | P741: 0 | Q741: =_xlfn.XLOOKUP(A741,工作表1!$A:$A,工作表1!$Q:$Q) -> 鋼筋
A742: 2028 | B742: 威致 | C742: 2022 | D742: 8317702 | E742: 387670 | F742: 185531 | G742: 1345100 | H742: 1223628 | I742: 13123335 | J742: -0.033 | K742: 1200158 | L742: -259942 | M742: 0.0595 | N742: 20.79 | O742: 181.8 | P742: 0 | Q742: =_xlfn.XLOOKUP(A742,工作表1!$A:$A,工作表1!$Q:$Q) -> 鋼筋
A743: 2029 | B743: 盛餘 | C743: 2024 | D743: 11512908 | E743: 151735 | F743: 0 | G743: 0 | H743: 1016460 | I743: 13690701 | J743: 0.1051 | K743: 519454 | L743: -362582 | M743: 0.0058 | N743: 214.36 | O743: 721.92 | P743: 1161 | Q743: =_xlfn.XLOOKUP(A743,工作表1!$A:$A,工作表1!$Q:$Q) -> 鋼板
A744: 2029 | B744: 盛餘 | C744: 2023 | D744: 10909791 | E744: 56699 | F744: 0 | G744: 0 | H744: 1054779 | I744: 12389155 | J744: -0.0318 | K744: 307385 | L744: -163164 | M744: 0.0052 | N744: 241.26 | O744: 968.37 | P744: -57680 | Q744: =_xlfn.XLOOKUP(A744,工作表1!$A:$A,工作表1!$Q:$Q) -> 鋼板
A745: 2029 | B745: 盛餘 | C745: 2022 | D745: 10627728 | E745: 143970 | F745: 0 | G745: 0 | H745: 939244 | I745: 12796257 | J745: -0.1087 | K745: 810986 | L745: -203675 | M745: 0.0089 | N745: 146.5 | O745: 975.94 | P745: 17884 | Q745: =_xlfn.XLOOKUP(A745,工作表1!$A:$A,工作表1!$Q:$Q) -> 鋼板
A746: 2030 | B746: 彰源 | C746: 2024 | D746: 12090108 | E746: 2664350 | F746: 554139 | G746: 2852992 | H746: 757267 | I746: 12398284 | J746: -0.0357 | K746: 633690 | L746: -268146 | M746: 0.4369 | N746: 2.97 | O746: 186.53 | P746: 41506 | Q746: =_xlfn.XLOOKUP(A746,工作表1!$A:$A,工作表1!$Q:$Q) -> 鋼管
A747: 2030 | B747: 彰源 | C747: 2023 | D747: 11877383 | E747: 2723232 | F747: 92069 | G747: 3345078 | H747: 537343 | I747: 12856899 | J747: -0.2087 | K747: -1041115 | L747: -401542 | M747: 0.8942 | N747: 1.58 | O747: 209.21 | P747: -42309 | Q747: =_xlfn.XLOOKUP(A747,工作表1!$A:$A,工作表1!$Q:$Q) -> 鋼管
... A906: 2258 | B906: 鴻華先進-創 | C906: 2023 | D906: 21244694 | E906: 0 | F906: 0 | G906: 0 | H906: -974533 | I906: 1043992 | J906: 2.5266 | K906: -6576245 | L906: -770048 | M906: -0.0006 | N906: -1852.49 | O906: 763.06 | P906: -691 | Q906: =_xlfn.XLOOKUP(A906,工作表1!$A:$A,工作表1!$Q:$Q) -> 汽車製造
A907: 2258 | B907: 鴻華先進-創 | C907: 2022 | D907: 14178617 | E907: 0 | F907: 0 | G907: 0 | H907: -789505 | I907: 296033 | J907: 3.4705 | K907: 1137432 | L907: -66391 | M907: 0 | O907: 645.62 | P907: 0 | Q907: =_xlfn.XLOOKUP(A907,工作表1!$A:$A,工作表1!$Q:$Q) -> 汽車製造
A908: 2301 | B908: 光寶科 | C908: 2024 | D908: 204682769 | E908: 30187483 | F908: 0 | G908: 3000000 | H908: 21197613 | I908: 137133894 | J908: -0.0755 | K908: 8828467 | L908: -3548191 | M908: 0.1151 | N908: 11.31 | O908: 156.78 | P908: 3736477 | Q908: =_xlfn.XLOOKUP(A908,工作表1!$A:$A,工作表1!$Q:$Q) -> 電源供應器
A909: 2301 | B909: 光寶科 | C909: 2023 | D909: 188972260 | E909: 22493450 | F909: 0 | G909: 3000000 | H909: 24223073 | I909: 148333455 | J909: -0.1448 | K909: 10806621 | L909: -3703048 | M909: 0.095 | N909: 13.23 | O909: 158.79 | P909: -203935 | Q909: =_xlfn.XLOOKUP(A909,工作表1!$A:$A,工作表1!$Q:$Q) -> 電源供應器
A910: 2301 | B910: 光寶科 | C910: 2022 | D910: 199781737 | E910: 32628984 | F910: 0 | G910: 3000000 | H910: 23102899 | I910: 173456216 | J910: 0.0523 | K910: 476106 | L910: -4249324 | M910: 0.0502 | N910: 25.03 | O910: 147.57 | P910: 4378249 | Q910: =_xlfn.XLOOKUP(A910,工作表1!$A:$A,工作表1!$Q:$Q) -> 電源供應器
A911: 2302 | B911: 麗正 | C911: 2024 | D911: 2645783 | E911: 0 | F911: 0 | G911: 0 | H911: 207963 | I911: 757457 | J911: 0.0571 | K911: 237649 | L911: -44161 | M911: 0.0024 | N911: 517.96 | O911: 133.25 | P911: -14481 | Q911: =_xlfn.XLOOKUP(A911,工作表1!$A:$A,工作表1!$Q:$Q) -> 分離式元件
A912: 2302 | B912: 麗正 | C912: 2023 | D912: 2334302 | E912: 15000 | F912: 0 | G912: 0 | H912: 161706 | I912: 716545 | J912: -0.1835 | K912: 161208 | L912: -6144 | M912: 0.0068 | N912: 180.22 | O912: 171.76 | P912: -29029 | Q912: =_xlfn.XLOOKUP(A912,工作表1!$A:$A,工作表1!$Q:$Q) -> 分離式元件
A913: 2302 | B913: 麗正 | C913: 2022 | D913: 2154019 | E913: 30000 | F913: 0 | G913: 0 | H913: 263571 | I913: 877633 | J913: 0.1767 | K913: 121083 | L913: -32474 | M913: 0.0064 | N913: 180.99 | O913: 264.52 | P913: -14970 | Q913: =_xlfn.XLOOKUP(A913,工作表1!$A:$A,工作表1!$Q:$Q) -> 分離式元件
A914: 2303 | B914: 聯電 | C914: 2024 | D914: 570200677 | E914: 8515000 | F914: 10994998 | G914: 30948500 | H914: 106143479 | I914: 232302584 | J914: 0.0439 | K914: 10095291 | L914: -88543595 | M914: 0.0362 | N914: 33.01 | O914: 252.03 | P914: 3715419 | Q914: =_xlfn.XLOOKUP(A914,工作表1!$A:$A,工作表1!$Q:$Q) -> 晶圓代工
A915: 2303 | B915: 聯電 | C915: 2023 | D915: 559186927 | E915: 13530000 | F915: 16006797 | G915: 20656248 | H915: 112966639 | I915: 222533000 | J915: -0.2015 | K915: 36473400 | L915: -91473668 | M915: 0.025 | N915: 46.16 | O915: 218.95 | P915: -392145 | Q915: =_xlfn.XLOOKUP(A915,工作表1!$A:$A,工作表1!$Q:$Q) -> 晶圓代工
A916: 2303 | B916: 聯電 | C916: 2022 | D916: 533052092 | E916: 0 | F916: 7586644 | G916: 16794289 | H916: 152133274 | I916: 278705264 | J916: 0.3084 | K916: 36074162 | L916: -80127628 | M916: 0.0209 | N916: 57.85 | O916: 232.46 | P916: 7018133 | Q916: =_xlfn.XLOOKUP(A916,工作表1!$A:$A,工作表1!$Q:$Q) -> 晶圓代工
A917: 2305 | B917: 全友 | C917: 2024 | D917: 2961524 | E917: 23000 | F917: 0 | G917: 0 | H917: 111544 | I917: 717115 | J917: 0.2452 | K917: -29549 | L917: -3787 | M917: 0.063 | N917: 16.88 | O917: 565.02 | P917: 16231 | Q917: =_xlfn.XLOOKUP(A917,工作表1!$A:$A,工作表1!$Q:$Q) -> 影像掃描
A918: 2305 | B918: 全友 | C918: 2023 | D918: 2863872 | E918: 50000 | F918: 0 | G918: 0 | H918: 91626 | I918: 575907 | J918: 0.0378 | K918: 8675 | L918: -2781 | M918: 0.1882 | N918: 9 | O918: 546.75 | P918: -2741 | Q918: =_xlfn.XLOOKUP(A918,工作表1!$A:$A,工作表1!$Q:$Q) -> 影像掃描
A919: 2305 | B919: 全友 | C919: 2022 | D919: 2944126 | E919: 107000 | F919: 0 | G919: 0 | H919: 88358 | I919: 554909 | J919: -0.1139 | K919: -16363 | L919: -4117 | M919: 0.2075 | N919: 7.95 | O919: 432.26 | P919: 2309 | Q919: =_xlfn.XLOOKUP(A919,工作表1!$A:$A,工作表1!$Q:$Q) -> 影像掃描
... A1483: 2646 | B1483: 星宇航空 | C1483: 2022 | D1483: 57088858 | E1483: 115523 | F1483: 4285809 | G1483: 9118118 | H1483: -3566039 | I1483: 3362135 | J1483: 3.2245 | K1483: -6875407 | L1483: -9428596 | M1483: -0.085 | N1483: -14.71 | O1483: 31.3 | P1483: 1145329 | Q1483: =_xlfn.XLOOKUP(A1483,工作表1!$A:$A,工作表1!$Q:$Q) -> 空運
A1484: 2701 | B1484: 萬企 | C1484: 2024 | D1484: 9782220 | E1484: 0 | F1484: 0 | G1484: 0 | H1484: 279395 | I1484: 290002 | J1484: -0.0242 | K1484: 135038 | L1484: -391 | M1484: 0 | O1484: 1226.97 | P1484: 0 | Q1484: =_xlfn.XLOOKUP(A1484,工作表1!$A:$A,工作表1!$Q:$Q) -> 飯店
A1485: 2701 | B1485: 萬企 | C1485: 2023 | D1485: 9560908 | E1485: 0 | F1485: 0 | G1485: 0 | H1485: 293416 | I1485: 297185 | J1485: 0.3113 | K1485: 142522 | L1485: -92 | M1485: 0 | O1485: 1084.77 | P1485: 0 | Q1485: =_xlfn.XLOOKUP(A1485,工作表1!$A:$A,工作表1!$Q:$Q) -> 飯店
A1486: 2701 | B1486: 萬企 | C1486: 2022 | D1486: 9162096 | E1486: 0 | F1486: 0 | G1486: 0 | H1486: 253273 | I1486: 226635 | J1486: -0.0554 | K1486: 118914 | L1486: -95 | M1486: 0 | O1486: 1216.49 | P1486: 0 | Q1486: =_xlfn.XLOOKUP(A1486,工作表1!$A:$A,工作表1!$Q:$Q) -> 飯店
A1487: 2702 | B1487: 華園 | C1487: 2024 | D1487: 8261277 | E1487: 400000 | F1487: 827677 | G1487: 3140952 | H1487: 637984 | I1487: 1441827 | J1487: 0.0061 | K1487: 1098719 | L1487: -46113 | M1487: 1.078 | N1487: 1.23 | O1487: 236.32 | P1487: 104656 | Q1487: =_xlfn.XLOOKUP(A1487,工作表1!$A:$A,工作表1!$Q:$Q) -> 飯店
A1488: 2702 | B1488: 華園 | C1488: 2023 | D1488: 8303860 | E1488: 400000 | F1488: 122430 | G1488: 4016071 | H1488: 563567 | I1488: 1433125 | J1488: 0.0505 | K1488: -310998 | L1488: -5131 | M1488: 1.1407 | N1488: 0.77 | O1488: 465.95 | P1488: 2446 | Q1488: =_xlfn.XLOOKUP(A1488,工作表1!$A:$A,工作表1!$Q:$Q) -> 飯店
A1489: 2702 | B1489: 華園 | C1489: 2022 | D1489: 8648934 | E1489: 484000 | F1489: 742587 | G1489: 3579764 | H1489: 1244894 | I1489: 1364208 | J1489: 0.6613 | K1489: -203292 | L1489: -30521 | M1489: 0.3593 | N1489: 4.59 | O1489: 247.04 | P1489: 120293 | Q1489: =_xlfn.XLOOKUP(A1489,工作表1!$A:$A,工作表1!$Q:$Q) -> 飯店
A1490: 2704 | B1490: 國賓 | C1490: 2024 | D1490: 34340316 | E1490: 0 | F1490: 0 | G1490: 0 | H1490: 1520000 | I1490: 1302587 | J1490: 0.0185 | K1490: -4671628 | L1490: -295160 | M1490: 0.0455 | N1490: 26.58 | O1490: 798.01 | P1490: 0 | Q1490: =_xlfn.XLOOKUP(A1490,工作表1!$A:$A,工作表1!$Q:$Q) -> 飯店
A1491: 2704 | B1491: 國賓 | C1491: 2023 | D1491: 25685921 | E1491: 0 | F1491: 0 | G1491: 0 | H1491: 961295 | I1491: 1278949 | J1491: -0.1176 | K1491: -3641312 | L1491: -376741 | M1491: 0.0959 | N1491: 14.15 | O1491: 730.66 | P1491: 0 | Q1491: =_xlfn.XLOOKUP(A1491,工作表1!$A:$A,工作表1!$Q:$Q) -> 飯店
A1492: 2704 | B1492: 國賓 | C1492: 2022 | D1492: 18642822 | E1492: 0 | F1492: 0 | G1492: 0 | H1492: 1488496 | I1492: 1449384 | J1492: -0.0454 | K1492: -4552182 | L1492: -400954 | M1492: 0.0435 | N1492: 23.47 | O1492: 783.19 | P1492: 0 | Q1492: =_xlfn.XLOOKUP(A1492,工作表1!$A:$A,工作表1!$Q:$Q) -> 飯店
A1493: 2705 | B1493: 六福 | C1493: 2024 | D1493: 15427153 | E1493: 0 | F1493: 98100 | G1493: 5080052 | H1493: 837013 | I1493: 2324483 | J1493: 0.0513 | K1493: 311435 | L1493: -104788 | M1493: 0.7974 | N1493: 1.45 | O1493: 52.4 | P1493: 2108 | Q1493: =_xlfn.XLOOKUP(A1493,工作表1!$A:$A,工作表1!$Q:$Q) -> 飯店
A1494: 2705 | B1494: 六福 | C1494: 2023 | D1494: 15639317 | E1494: 53500 | F1494: 234506 | G1494: 4769815 | H1494: 657323 | I1494: 2211095 | J1494: 0.3199 | K1494: -138985 | L1494: -116332 | M1494: 3.1941 | N1494: 0.51 | O1494: 42.61 | P1494: 21 | Q1494: =_xlfn.XLOOKUP(A1494,工作表1!$A:$A,工作表1!$Q:$Q) -> 飯店
A1495: 2705 | B1495: 六福 | C1495: 2022 | D1495: 15772505 | E1495: 413500 | F1495: 377540 | G1495: 4017610 | H1495: 404423 | I1495: 1675217 | J1495: 0.3327 | K1495: 532109 | L1495: -111348 | M1495: -0.9838 | N1495: -0.82 | O1495: 30.92 | P1495: 3024 | Q1495: =_xlfn.XLOOKUP(A1495,工作表1!$A:$A,工作表1!$Q:$Q) -> 飯店
...

Sheet 工作表1
A1: ID | B1: Name | C1: Year | D1: Assets | E1: STD | F1: CPLTD | G1: LTD | H1: EBITDA | I1: Sales | J1: Sales_YOY | K1: FCF | L1: CapEx | M1: Int | N1: TIE | O1: CR | P1: FX | Q1: Industry
A2: 1101 | B2: 台泥 | C2: 45627 | D2: 593413647 | E2: 24292290 | F2: 9307637 | G2: 61287926 | H2: 44556263 | I2: 154606511 | J2: 41.43 | K2: -7979225 | L2: -33603520 | M2: 26.49 | N2: 5.35 | O2: 200.73 | P2: 2488775 | Q2: 水泥製造
A3: 1102 | B3: 亞泥 | C3: 45627 | D3: 331827224 | E3: 26488506 | F3: 18871785 | G3: 8926787 | H3: 22257323 | I3: 81848827 | J3: -0.87 | K3: 15731708 | L3: -4003258 | M3: 11.92 | N3: 10.6 | O3: 146.4 | P3: 1397272 | Q3: 水泥製造
A4: 1103 | B4: 嘉泥 | C4: 45627 | D4: 35078080 | E4: 885000 | F4: 1055745 | G4: 6879673 | H4: 1049811 | I4: 2985357 | J4: 2.53 | K4: 1058475 | L4: -51631 | M4: 42.3 | N4: 2.79 | O4: 336.63 | P4: 46319 | Q4: 水泥製造
A5: 1104 | B5: 環泥 | C5: 45627 | D5: 29627506 | E5: 2100000 | F5: 0 | G5: 0 | H5: 2070596 | I5: 7953734 | J5: 1.94 | K5: 948645 | L5: -179647 | M5: 2.74 | N5: 43.09 | O5: 188.97 | P5: 0 | Q5: 水泥製造
A6: 1108 | B6: 幸福 | C6: 45627 | D6: 10431267 | E6: 1613112 | F6: 428000 | G6: 872500 | H6: 827725 | I6: 4867094 | J6: -4.47 | K6: 917334 | L6: -570866 | M6: 9.33 | N6: 13.18 | O6: 144.08 | P6: 251 | Q6: 水泥製造
A7: 1109 | B7: 信大 | C7: 45627 | D7: 11279234 | E7: 0 | F7: 0 | G7: 0 | H7: 1025055 | I7: 4656290 | J7: -25.62 | K7: 453026 | L7: -211756 | M7: 0.4 | N7: 336.87 | O7: 699.73 | P7: 82379 | Q7: 水泥製造
A8: 1110 | B8: 東泥 | C8: 45627 | D8: 12721937 | E8: 1266774 | F8: 50 | G8: 411320 | H8: 572398 | I8: 2872958 | J8: 26.37 | K8: 47092 | L8: -204807 | M8: 8.03 | N8: 14.42 | O8: 149.36 | P8: 0 | Q8: 水泥製造
A9: 1201 | B9: 味全 | C9: 45627 | D9: 17621082 | E9: 1821228 | F9: 18000 | G9: 2570000 | H9: 1888113 | I9: 23473804 | J9: 9.3 | K9: 241835 | L9: -734907 | M9: 23.57 | N9: 5.82 | O9: 103.91 | P9: 30508 | Q9: 飲料乳品
A10: 1203 | B10: 味王 | C10: 45627 | D10: 10278895 | E10: 777935 | F10: 126000 | G10: 0 | H10: 1373063 | I10: 6287463 | J10: -1.82 | K10: 630347 | L10: -129299 | M10: 2.56 | N10: 53.81 | O10: 268.69 | P10: 76917 | Q10: 其他食品
A11: 1210 | B11: 大成 | C11: 45627 | D11: 70755170 | E11: 16602929 | F11: 751521 | G11: 1669652 | H11: 9129286 | I11: 102749063 | J11: -7.52 | K11: 4177598 | L11: -4203213 | M11: 12.62 | N11: 10.06 | O11: 97.72 | P11: 507152 | Q11: 油脂飼料
A12: 1213 | B12: 大飲 | C12: 45627 | D12: 796039 | E12: 0 | F12: 0 | G12: 0 | H12: 546467 | I12: 190548 | J12: 57.87 | K12: -304537 | L12: -3305 | M12: 2.55 | N12: 41.41 | O12: 485.23 | P12: 3 | Q12: 飲料乳品
A13: 1215 | B13: 卜蜂 | C13: 45627 | D13: 29463806 | E13: 3398000 | F13: 1326311 | G13: 8644785 | H13: 3738582 | I13: 27957258 | J13: -4.12 | K13: 2086719 | L13: -2579743 | M13: 11.93 | N13: 10.42 | O13: 81.8 | P13: 3079 | Q13: 油脂飼料
... A125: 1526 | B125: 日馳 | C125: 45627 | D125: 2444138 | E125: 90955 | F125: 11100 | G125: 273543 | H125: 34555 | I125: 720682 | J125: -27.58 | K125: 134243 | L125: -18505 | M125: -56.92 | N125: -2.22 | O125: 472.75 | P125: 14688 | Q125: 自行車組件
A126: 1527 | B126: 鑽全 | C126: 45627 | D126: 5558752 | E126: 0 | F126: 0 | G126: 0 | H126: 682523 | I126: 3130242 | J126: 12.43 | K126: 842032 | L126: -140094 | M126: 0 | O126: 591.17 | P126: 0 | Q126: 工具機
A127: 1528 | B127: 恩德 | C127: 45627 | D127: 5305871 | E127: 1542608 | F127: 268122 | G127: 355633 | H127: 42020 | I127: 3672594 | J127: -5.42 | K127: 207148 | L127: -113543 | M127: -53.33 | N127: -1.57 | O127: 141.47 | P127: 9149 | Q127: 工具機
A128: 1529 | B128: 樂事綠能 | C128: 45627 | D128: 3384566 | E128: 275000 | F128: 62389 | G128: 816396 | H128: 143995 | I128: 696439 | J128: -7.43 | K128: 86963 | L128: -200327 | M128: 718.49 | N128: 0.9 | O128: 159.65 | P128: 0 | Q128: 電機
A129: 1530 | B129: 亞崴 | C129: 45627 | D129: 6393258 | E129: 1613983 | F129: 0 | G129: 0 | H129: 598714 | I129: 1917762 | J129: -18.8 | K129: 154770 | L129: -183694 | M129: 6.65 | N129: 15.59 | O129: 166.88 | P129: 14778 | Q129: 工具機
A130: 1531 | B130: 高林股 | C130: 45627 | D130: 4371229 | E130: 100000 | F130: 0 | G130: 0 | H130: 188585 | I130: 1637783 | J130: 15.29 | K130: -42814 | L130: -47070 | M130: 2.65 | N130: 47.8 | O130: 805.97 | P130: 18550 | Q130: 紡織工具機
A131: 1532 | B131: 勤美 | C131: 45627 | D131: 52845077 | E131: 12260016 | F131: 1385893 | G131: 7637096 | H131: 3276749 | I131: 18019849 | J131: 2.27 | K131: 1676496 | L131: -1264655 | M131: 20.4 | N131: 5.92 | O131: 141.34 | P131: 121003 | Q131: 模具零件
A132: 1533 | B132: 車王電 | C132: 45627 | D132: 8624480 | E132: 1396649 | F132: 1766027 | G132: 1137247 | H132: 138072 | I132: 3345244 | J132: -16.44 | K132: 1156989 | L132: -86619 | M132: -84.87 | N132: -0.86 | O132: 119.56 | P132: 140029 | Q132: 汽車組件
A133: 1535 | B133: 中宇 | C133: 45627 | D133: 7157430 | E133: 50000 | F133: 0 | G133: 0 | H133: 706115 | I133: 10858807 | J133: 11.27 | K133: 725055 | L133: -166971 | M133: 0.45 | N133: 278.16 | O133: 135.55 | P133: 20985 | Q133: 機電工程
A134: 1536 | B134: 和大 | C134: 45627 | D134: 22442497 | E134: 2834642 | F134: 1544738 | G134: 5242253 | H134: 1134470 | I134: 5774470 | J134: -12.5 | K134: 500341 | L134: -526174 | M134: 53.54 | N134: 2.28 | O134: 112.22 | P134: 76331 | Q134: 汽車組件
A135: 1537 | B135: 廣隆 | C135: 45627 | D135: 6317970 | E135: 48614 | F135: 0 | G135: 0 | H135: 1447085 | I135: 8137839 | J135: 26.82 | K135: 425496 | L135: -121509 | M135: 0.06 | N135: 2187.63 | O135: 455.18 | P135: 172836 | Q135: 二次電池
A136: 1538 | B136: 正峰 | C136: 45627 | D136: 271904 | E136: 7055 | F136: 0 | G136: 0 | H136: -39442 | I136: 112684 | J136: -42.04 | K136: -12098 | L136: -8508 | M136: -0.92 | N136: -105.19 | O136: 269.36 | P136: 21958 | Q136: 工具機
A137: 1539 | B137: 巨庭 | C137: 45627 | D137: 2253146 | E137: 80000 | F137: 28831 | G137: 195342 | H137: 175160 | I137: 1338821 | J137: -12.69 | K137: 168514 | L137: -21276 | M137: 6.7 | N137: 18.67 | O137: 272.12 | P137: 59 | Q137: 工具機
A138: 1540 | B138: 喬福 | C138: 45627 | D138: 1828680 | E138: 0 | F138: 0 | G138: 0 | H138: 234524 | I138: 498100 | J138: -13.48 | K138: 80913 | L138: -4442 | M138: 0 | O138: 515.34 | P138: -73 | Q138: 工具機
A139: 1541 | B139: 錩泰 | C139: 45627 | D139: 3157599 | E139: 16000 | F139: 0 | G139: 0 | H139: 239701 | I139: 2988448 | J139: -11.53 | K139: 221713 | L139: -12468 | M139: 19.36 | N139: 6.13 | O139: 242.43 | P139: 30229 | Q139: 工具機
A140: 1558 | B140: 伸興 | C140: 45627 | D140: 13140704 | E140: 906000 | F140: 107525 | G140: 616177 | H140: 1885894 | I140: 8337227 | J140: 10.31 | K140: 1357424 | L140: -451003 | M140: 2.34 | N140: 55.8 | O140: 225.4 | P140: 61794 | Q140: 紡織工具機
A141: 1560 | B141: 中砂 | C141: 45627 | D141: 11050863 | E141: 60500 | F141: 14383 | G141: 1078219 | H141: 1910886 | I141: 7019493 | J141: 10.01 | K141: -678805 | L141: -348508 | M141: 4.02 | N141: 30.23 | O141: 355.04 | P141: 26268 | Q141: 晶圓材料
A142: 1563 | B142: 巧新 | C142: 45627 | D142: 17519544 | E142: 1003535 | F142: 1027626 | G142: 4260544 | H142: 2017197 | I142: 7473579 | J142: -3.93 | K142: 219882 | L142: -487406 | M142: 17.82 | N142: 7.01 | O142: 273.06 | P142: -1036 | Q142: 汽車組件
A143: 1565 | B143: 精華 | C143: 45627 | D143: 8100886 | E143: 0 | F143: 103132 | G143: 186107 | H143: 1232467 | I143: 4550058 | J143: 3.55 | K143: 536490 | L143: -93115 | M143: 1.18 | N143: 106.91 | O143: 343.22 | P143: 64 | Q143: 輔助與彌補
A144: 1568 | B144: 倉佑 | C144: 45627 | D144: 2326550 | E144: 0 | F144: 55034 | G144: 65078 | H144: 297230 | I144: 1049324 | J144: -12.05 | K144: 369363 | L144: -175279 | M144: 2.43 | N144: 53.37 | O144: 278.55 | P144: -4003 | Q144: 汽車組件
A145: 1569 | B145: 濱川 | C145: 45627 | D145: 6400654 | E145: 1215326 | F145: 175467 | G145: 633303 | H145: 290312 | I145: 3103113 | J145: -13.93 | K145: 379177 | L145: -453465 | M145: -19.18 | N145: -4.78 | O145: 123.61 | P145: 106005 | Q145: 機殼
A146: 1570 | B146: 力肯 | C146: 45627 | D146: 1206637 | E146: 0 | F146: 0 | G146: 0 | H146: 152452 | I146: 730104 | J146: 85.47 | K146: 23292 | L146: -2177 | M146: 0.22 | N146: 544.78 | O146: 522.05 | P146: 244 | Q146: 工具機
A147: 1580 | B147: 新麥 | C147: 45627 | D147: 4466841 | E147: 0 | F147: 16561 | G147: 0 | H147: 1215754 | I147: 4792059 | J147: 6.52 | K147: 533964 | L147: -179694 | M147: 0.18 | N147: 810.27 | O147: 272.86 | P147: 31614 | Q147: 儀器設備
A148: 1582 | B148: 信錦 | C148: 45627 | D148: 13180799 | E148: 1704290 | F148: 21650 | G148: 173119 | H148: 2125830 | I148: 9404071 | J148: 7.24 | K148: 44926 | L148: -236091 | M148: 4.26 | N148: 36.54 | O148: 224.77 | P148: 110468 | Q148: 沖壓零組件
A149: 1583 | B149: 程泰 | C149: 45627 | D149: 14851237 | E149: 2986248 | F149: 77450 | G149: 996063 | H149: 1853535 | I149: 4422922 | J149: -16.84 | K149: -351072 | L149: -367515 | M149: 5.33 | N149: 19.75 | O149: 219.25 | P149: 64801 | Q149: 工具機
A150: 1584 | B150: 精剛 | C150: 45627 | D150: 7860166 | E150: 1166735 | F150: 16667 | G150: 1039967 | H150: 528632 | I150: 2880076 | J150: 4.79 | K150: -839591 | L150: -1842068 | M150: 13.33 | N150: 8.82 | O150: 230.2 | P150: 0 | Q150: 不鏽鋼
... A206: 1781 | B206: 合世 | C206: 45627 | D206: 817262 | E206: 0 | F206: 12612 | G206: 6306 | H206: 55630 | I206: 706388 | J206: 17.5 | K206: -165526 | L206: -3105 | M206: 12.53 | N206: 9.52 | O206: 262.05 | P206: 4075 | Q206: 診斷與監測
A207: 1783 | B207: 和康生 | C207: 45627 | D207: 1582489 | E207: 0 | F207: 0 | G207: 0 | H207: 252569 | I207: 680651 | J207: 9.41 | K207: 49145 | L207: -31771 | M207: 0 | O207: 403.33 | P207: -1450 | Q207: 輔助與彌補
A208: 1784 | B208: 訊聯 | C208: 45627 | D208: 3156241 | E208: 65000 | F208: 0 | G208: 0 | H208: 149085 | I208: 1222030 | J208: 8.4 | K208: -647066 | L208: -101347 | M208: 1.8 | N208: 80.94 | O208: 506.19 | P208: 491 | Q208: 細胞醫療
A209: 1785 | B209: 光洋科 | C209: 45627 | D209: 31292876 | E209: 4146089 | F209: 2886031 | G209: 5022938 | H209: 3311330 | I209: 29769958 | J209: 31.56 | K209: 1938557 | L209: -553077 | M209: 14.22 | N209: 8.75 | O209: 193.84 | P209: 98855 | Q209: 貴金屬回收
A210: 1786 | B210: 科妍 | C210: 45627 | D210: 2354476 | E210: 0 | F210: 134785 | G210: 0 | H210: 362499 | I210: 883310 | J210: 23.89 | K210: 302287 | L210: -34763 | M210: 2.3 | N210: 52.4 | O210: 346.05 | P210: 50 | Q210: 輔助與彌補
A211: 1788 | B211: 杏昌 | C211: 45627 | D211: 4960390 | E211: 367987 | F211: 0 | G211: 0 | H211: 647829 | I211: 4072811 | J211: 4.54 | K211: 560444 | L211: -282741 | M211: 3.73 | N211: 33.95 | O211: 177.17 | P211: 3124 | Q211: 手術與治療
A212: 1789 | B212: 神隆 | C212: 45627 | D212: 11942738 | E212: 35563 | F212: 0 | G212: 0 | H212: 909381 | I212: 3406284 | J212: 6.91 | K212: 358209 | L212: -280169 | M212: 2.34 | N212: 52.1 | O212: 860.78 | P212: 11820 | Q212: 原料藥
A213: 1795 | B213: 美時 | C213: 45627 | D213: 40101143 | E213: 1614619 | F213: 3389979 | G213: 8383528 | H213: 8213596 | I213: 18584227 | J213: 9.59 | K213: 4463366 | L213: -353838 | M213: 10.34 | N213: 12.14 | O213: 214.48 | P213: 80996 | Q213: 學名藥
A214: 1796 | B214: 金穎生技 | C214: 45627 | D214: 1146495 | E214: 0 | F214: 24429 | G214: 126536 | H214: 56338 | I214: 521163 | J214: -34.34 | K214: -36006 | L214: -22398 | M214: -23.42 | N214: -5.18 | O214: 306.85 | P214: 653 | Q214: 機能性食品
A215: 1799 | B215: 易威 | C215: 45627 | D215: 1505307 | E215: 201086 | F215: 0 | G215: 0 | H215: 12753 | I215: 540438 | J215: 98.96 | K215: -35475 | L215: -12491 | M215: -29.58 | N215: -3.17 | O215: 193.1 | P215: 6405 | Q215: 學名藥
A216: 1802 | B216: 台玻 | C216: 45627 | D216: 90375732 | E216: 5612065 | F216: 8080000 | G216: 5820000 | H216: 4074988 | I216: 42502810 | J216: -6.83 | K216: 3498528 | L216: -4069091 | M216: -51.79 | N216: -0.98 | O216: 116.67 | P216: 648929 | Q216: 玻璃陶瓷
A217: 1805 | B217: 寶徠 | C217: 45627 | D217: 2069487 | E217: 330980 | F217: 0 | G217: 0 | H217: 335227 | I217: 625467 | J217: 329.83 | K217: -112366 | L217: -519 | M217: 5.09 | N217: 20.49 | O217: 214.01 | P217: -26 | Q217: 建設
A218: 1806 | B218: 冠軍 | C218: 45627 | D218: 8315978 | E218: 98953 | F218: 68166 | G218: 1323876 | H218: 564168 | I218: 3429476 | J218: 9.3 | K218: -1578363 | L218: -642884 | M218: 26.86 | N218: 5.4 | O218: 411.33 | P218: 7059 | Q218: 玻璃陶瓷
A219: 1808 | B219: 潤隆 | C219: 45627 | D219: 51513261 | E219: 17451932 | F219: 26409 | G219: 241276 | H219: 2968286 | I219: 8787971 | J219: -71.36 | K219: -2133754 | L219: -5095 | M219: 6.27 | N219: 19.48 | O219: 172.96 | P219: 0 | Q219: 建設
... A495: 2646 | B495: 星宇航空 | C495: 45627 | D495: 119064801 | E495: 0 | F495: 1853339 | G495: 36996425 | H495: 7933815 | I495: 35546851 | J495: 58.18 | K495: -33105158 | L495: -29600504 | M495: 46.41 | N495: 2.32 | O495: 113.32 | P495: 47861 | Q495: 空運
A496: 2701 | B496: 萬企 | C496: 45627 | D496: 9782220 | E496: 0 | F496: 0 | G496: 0 | H496: 279395 | I496: 290002 | J496: -2.42 | K496: 135038 | L496: -391 | M496: 0 | O496: 1226.97 | P496: 0 | Q496: 飯店
A497: 2702 | B497: 華園 | C497: 45627 | D497: 8261277 | E497: 400000 | F497: 827677 | G497: 3140952 | H497: 637984 | I497: 1441827 | J497: 0.61 | K497: 1098719 | L497: -46113 | M497: 107.8 | N497: 1.23 | O497: 236.32 | P497: 104656 | Q497: 飯店
A498: 2704 | B498: 國賓 | C498: 45627 | D498: 34340316 | E498: 0 | F498: 0 | G498: 0 | H498: 1520000 | I498: 1302587 | J498: 1.85 | K498: -4671628 | L498: -295160 | M498: 4.55 | N498: 26.58 | O498: 798.01 | P498: 0 | Q498: 飯店
A499: 2705 | B499: 六福 | C499: 45627 | D499: 15427153 | E499: 0 | F499: 98100 | G499: 5080052 | H499: 837013 | I499: 2324483 | J499: 5.13 | K499: 311435 | L499: -104788 | M499: 79.74 | N499: 1.45 | O499: 52.4 | P499: 2108 | Q499: 飯店
A500: 2706 | B500: 第一店 | C500: 45627 | D500: 11741559 | E500: 0 | F500: 0 | G500: 0 | H500: 347828 | I500: 355880 | J500: 3.67 | K500: 191869 | L500: -2050 | M500: 0.69 | N500: 179.38 | O500: 2171.37 | P500: 0 | Q500: 飯店
A501: 2707 | B501: 晶華 | C501: 45627 | D501: 10950343 | E501: 86714 | F501: 0 | G501: 0 | H501: 2316700 | I501: 6296962 | J501: -6.92 | K501: 1850032 | L501: -417862 | M501: 3.9 | N501: 31.94 | O501: 157.7 | P501: 14429 | Q501: 飯店
A502: 2712 | B502: 遠雄來 | C502: 45627 | D502: 1808882 | E502: 10000 | F502: 40000 | G502: 336923 | H502: -47042 | I502: 354975 | J502: -45.9 | K502: -72212 | L502: -106473 | M502: -5.18 | N502: -19.1 | O502: 41.5 | P502: 0 | Q502: 飯店
A503: 2718 | B503: 全心投資控股 | C503: 45627 | D503: 6425960 | E503: 262728 | F503: 0 | G503: 0 | H503: 3308870 | I503: 4251276 | J503: 95.41 | K503: 540954 | L503: 0 | M503: 0.18 | N503: 594.56 | O503: 532.7 | P503: 0 | Q503: 建設
A504: 2719 | B504: 燦星旅 | C504: 45627 | D504: 1171642 | E504: 0 | F504: 4087 | G504: 72240 | H504: 104242 | I504: 2286931 | J504: 108.42 | K504: 76529 | L504: -8862 | M504: 3.07 | N504: 32.42 | O504: 208.79 | P504: 0 | Q504: 旅行社
A505: 2722 | B505: 夏都 | C505: 45627 | D505: 3676300 | E505: 74733 | F505: 33695 | G505: 67243 | H505: 115773 | I505: 631447 | J505: -17.44 | K505: -168644 | L505: -47035 | M505: -379.75 | N505: 0.02 | O505: 173.73 | P505: 0 | Q505: 飯店
A506: 2727 | B506: 王品 | C506: 45627 | D506: 16288607 | E506: 0 | F506: 0 | G506: 0 | H506: 3967388 | I506: 22290529 | J506: -0.12 | K506: 2098113 | L506: -1093722 | M506: 7.72 | N506: 16.27 | O506: 120.39 | P506: 39452 | Q506: 餐飲
A507: 2729 | B507: 瓦城 | C507: 45627 | D507: 5646305 | E507: 250000 | F507: 132301 | G507: 452928 | H507: 1137626 | I507: 6075752 | J507: 6.16 | K507: 242522 | L507: -730984 | M507: 5.05 | N507: 24.97 | O507: 79.13 | P507: 2867 | Q507: 餐飲
A508: 2731 | B508: 雄獅 | C508: 45627 | D508: 10453623 | E508: 13000 | F508: 34386 | G508: 37773 | H508: 1463540 | I508: 28326933 | J508: 30.74 | K508: 698036 | L508: -218527 | M508: 1.82 | N508: 71.07 | O508: 140.62 | P508: 9746 | Q508: 旅行社
... A527: 2761 | B527: 橘焱胡同 | C527: 45627 | D527: 1143234 | E527: 145780 | F527: 28700 | G527: 104187 | H527: 151855 | I527: 1205877 | J527: 23.26 | K527: 32777 | L527: -145505 | M527: 73.29 | N527: 1.76 | O527: 93.22 | P527: 4920 | Q527: 餐飲
A528: 2801 | B528: 彰銀 | C528: 45627 | D528: 3172721131 | E528: 0 | H528: 73471445 | I528: 41819537 | J528: 8.42 | L528: -1162037 | P528: 2315673 | Q528: 本國銀行
A529: 2812 | B529: 台中銀 | C529: 45627 | D529: 972079102 | E529: 0 | H529: 23371809 | I529: 19299219 | J529: 10.3 | L529: -1077923 | P529: 83737 | Q529: 本國銀行
A530: 2816 | B530: 旺旺保 | C530: 45627 | D530: 23230597 | E530: 0 | H530: 1552660 | I530: 11016347 | J530: 8.24 | L530: -47392 | N530: 155.45 | P530: 0 | Q530: 產險
A531: 2820 | B531: 華票 | C531: 45627 | D531: 252726909 | E531: 0 | H531: 5533105 | I531: 2238530 | J531: 10.87 | L531: -19784 | P531: 0 | Q531: 票券公司
A532: 2832 | B532: 台產 | C532: 45627 | D532: 24909836 | E532: 0 | H532: 1447295 | I532: 7340275 | J532: 8.45 | L532: -8093 | P532: 0 | Q532: 產險
A533: 2834 | B533: 臺企銀 | C533: 45627 | D533: 2374756050 | E533: 0 | H533: 51753724 | I533: 34114587 | J533: 6.9 | L533: -470352 | P533: 22868 | Q533: 本國銀行
A534: 2836 | B534: 高雄銀 | C534: 45627 | D534: 350650438 | E534: 0 | H534: 6873360 | I534: 4384596 | J534: 14.76 | L534: -333282 | P534: -869 | Q534: 本國銀行
A535: 2838 | B535: 聯邦銀 | C535: 45627 | D535: 995457466 | E535: 0 | H535: 22853831 | I535: 19826869 | J535: 10.55 | L535: -1382900 | P535: 39438 | Q535: 本國銀行
A536: 2845 | B536: 遠東銀 | C536: 45627 | D536: 853463050 | E536: 480000 | H536: 19546134 | I536: 12857713 | J536: 0.5 | L536: -371663 | P536: 849869 | Q536: 本國銀行
A537: 2849 | B537: 安泰銀 | C537: 45627 | D537: 363916229 | E537: 0 | H537: 7630902 | I537: 5543699 | J537: -4.79 | L537: -67092 | P537: 143958 | Q537: 本國銀行
A538: 2850 | B538: 新產 | C538: 45627 | D538: 54607964 | E538: 0 | H538: 4107191 | I538: 20853743 | J538: 4.59 | L538: -60872 | P538: 0 | Q538: 產險
A539: 2851 | B539: 中再保 | C539: 45627 | D539: 57853650 | E539: 0 | I539: 22886773 | J539: 4.13 | L539: -3026 | N539: 148238.1 | P539: 82547 | Q539: 產險
A540: 2852 | B540: 第一保 | C540: 45627 | D540: 19706605 | E540: 0 | H540: 1124022 | I540: 7799051 | J540: 5.47 | L540: -9739 | P540: 3333 | Q540: 產險
A541: 2855 | B541: 統一證 | C541: 45627 | D541: 193473197 | E541: 8804220 | F541: 0 | G541: 0 | H541: 6890006 | I541: 13029981 | J541: 36.55 | K541: 2034585 | L541: -256285 | M541: 28.32 | N541: 4.07 | O541: 116.11 | P541: -132307 | Q541: 證券
A542: 2867 | B542: 三商壽 | C542: 45627 | D542: 1625142670 | E542: 0 | H542: 745255 | I542: 136846587 | J542: 11.01 | L542: -58019 | P542: 0 | Q542: 壽險
A543: 2880 | B543: 華南金 | C543: 45627 | D543: 4246261896 | E543: 0 | H543: 105868867 | I543: 66778791 | J543: 12.29 | L543: -1823625 | M543: 90.08 | P543: 2662349 | Q543: 金融控股
A544: 2881 | B544: 富邦金 | C544: 45627 | D544: 12067311207 | E544: 0 | H544: 303952348 | I544: 347463495 | J544: 107.07 | L544: -4700054 | M544: 49.5 | P544: 9190045 | Q544: 金融控股
A545: 2882 | B545: 國泰金 | C545: 45627 | D545: 13767150337 | E545: 0 | H545: 202702211 | I545: 357716917 | J545: 17.6 | L545: -4978849 | M545: 41.07 | P545: 130830 | Q545: 金融控股
A546: 2883 | B546: 凱基金 | C546: 45627 | D546: 3948244504 | E546: 0 | H546: 74167635 | I546: 73288769 | J546: 85.3 | L546: -900986 | M546: 51.02 | P546: -137658 | Q546: 金融控股
A547: 2884 | B547: 玉山金 | C547: 45627 | D547: 4068237577 | E547: 0 | H547: 102241408 | I547: 76144545 | J547: 14.17 | L547: -1655197 | M547: 83.69 | P547: -9067852 | Q547: 金融控股
A548: 2885 | B548: 元大金 | C548: 45627 | D548: 3715729804 | E548: 0 | H548: 88598418 | I548: 120699682 | J548: 23.05 | L548: -5425860 | M548: 56.19 | P548: 3479072 | Q548: 金融控股
A549: 2886 | B549: 兆豐金 | C549: 45627 | D549: 4671606749 | E549: 0 | H549: 134964913 | I549: 83485131 | J549: 7.97 | L549: -1270723 | M549: 85.29 | P549: 1858081 | Q549: 金融控股
A550: 2887 | B550: 台新新光金 | C550: 45627 | D550: 3290705344 | E550: 0 | H550: 78473536 | I550: 86608250 | J550: 23.87 | L550: -872989 | M550: 84.33 | P550: 6495 | Q550: 金融控股
A551: 2889 | B551: 國票金 | C551: 45627 | D551: 403677065 | E551: 0 | H551: 9565355 | I551: 8207387 | J551: 15.69 | L551: -121497 | M551: 77.97 | P551: 67709 | Q551: 金融控股
A552: 2890 | B552: 永豐金 | C552: 45627 | D552: 3068775166 | E552: 0 | H552: 87963019 | I552: 64423375 | J552: 19.52 | L552: -1541263 | M552: 84.59 | P552: 1204927 | Q552: 金融控股
A553: 2891 | B553: 中信金 | C553: 45627 | D553: 8839609949 | E553: 0 | H553: 207625899 | I553: 189409573 | J553: 38.68 | L553: -2850051 | M553: 68.32 | P553: 2860609 | Q553: 金融控股
A554: 2892 | B554: 第一金 | C554: 45627 | D554: 4704422325 | E554: 0 | H554: 119839874 | I554: 72119475 | J554: 7.23 | L554: -1228200 | M554: 91.39 | P554: 3932909 | Q554: 金融控股
A555: 2897 | B555: 王道銀行 | C555: 45627 | D555: 683085154 | E555: 63800 | H555: 19821186 | I555: 10178713 | J555: 6.65 | L555: -197290 | P555: 271543 | Q555: 本國銀行
A556: 2901 | B556: 欣欣 | C556: 45627 | D556: 1008536 | E556: 0 | F556: 0 | G556: 0 | H556: 59464 | I556: 133626 | J556: 0.23 | K556: 21930 | L556: -6580 | M556: 0.2 | N556: 671.78 | O556: 892.16 | P556: 0 | Q556: 百貨及Mall
A557: 2903 | B557: 遠百 | C557: 45627 | D557: 142263215 | E557: 14218418 | F557: 247799 | G557: 14158210 | H557: 11154426 | I557: 35006753 | J557: -4.68 | K557: 5786447 | L557: -1334234 | M557: 37.34 | N557: 3.34 | O557: 56.1 | P557: 38103 | Q557: 百貨及Mall
A558: 2904 | B558: 匯僑 | C558: 45627 | D558: 1969632 | E558: 0 | F558: 54474 | G558: 315265 | H558: 335046 | I558: 492033 | J558: 11.44 | K558: 123573 | L558: -47461 | M558: 10.26 | N558: 12.2 | O558: 150.68 | P558: 2379 | Q558: 貨運倉儲
A559: 2905 | B559: 三商 | C559: 45627 | D559: 1657801534 | E559: 1385100 | F559: 541364 | G559: 8269664 | H559: 4318674 | I559: 163405527 | J559: 2.13 | K559: 38595737 | L559: -2152307 | M559: 6.85 | N559: 6.41 | O559: 613.23 | P559: -2124 | Q559: 其他零售
...
